funcnodes_umap/__init__.py
funcnodes_umap-0.1.2.dist-info/METADATA
funcnodes_umap-0.1.2.dist-info/WHEEL
funcnodes_umap-0.1.2.dist-info/RECORD
