Metadata-Version: 2.1
Name: funcnodes-umap
Version: 0.1.2
Summary: 
Author: Julian Kimmig
Author-email: julian.kimmig@gmx.net
Requires-Python: >=3.10,<4.0
Classifier: Programming Language :: Python :: 3
Classifier: Programming Language :: Python :: 3.10
Classifier: Programming Language :: Python :: 3.11
Classifier: Programming Language :: Python :: 3.12
Requires-Dist: funcnodes (>=0.2.14,<0.3.0)
Requires-Dist: funcnodes-plotly (>=0.1.3,<0.2.0)
Requires-Dist: umap-learn (>=0.5.6,<0.6.0)
